pymesomake/__init__.py
pymesomake/__main__.py
pymesomake/pymesomake.py
pymesomake/pymesomake_test.py
pymesomake-0.4.1.dist-info/LICENSE
pymesomake-0.4.1.dist-info/METADATA
pymesomake-0.4.1.dist-info/WHEEL
pymesomake-0.4.1.dist-info/entry_points.txt
pymesomake-0.4.1.dist-info/top_level.txt
pymesomake-0.4.1.dist-info/RECORD
