Metadata-Version: 2.1
Name: pymesomake
Version: 0.4.1
Summary: An implementation of the mesostic generation algorithm Andrew Culver developed for John Cage.
Home-page: https://github.com/erictheise/pymesomake
Author: Eric Theise
Author-email: erictheise@gmail.com
License: UNKNOWN
Platform: UNKNOWN
Classifier: Programming Language :: Python :: 3
Classifier: License :: OSI Approved :: MIT License
Classifier: Operating System :: OS Independent
Requires-Dist: Click
Requires-Dist: nltk
